{}{"timestamp": "2025-09-24T05:23:44.176704", "run_id": "17967172930", "downloads": [{"success": true, "filepath": "downloads/urls_20250924_052303.txt", "filename": "urls_20250924_052303.txt", "size": 256, "hash": "a3fbce9fb7604b5bf9d832473ca4a4c3", "url": "http://www.zmyxl2016.com/urls.txt", "url_name": "屏蔽网址列表", "timestamp": "2025-09-24T05:23:04.472985"}, {"success": true, "filepath": "downloads/cpm_20250924_052304.txt", "filename": "cpm_20250924_052304.txt", "size": 29, "hash": "bbe7ab82f2f0b477f9b5fe107baa9d68", "url": "http://www.zmyxl2008.com/cpm.txt", "url_name": "屏蔽程序特征表", "timestamp": "2025-09-24T05:23:09.870141"}, {"success": true, "filepath": "downloads/jfgl2_20250924_052309.zip", "filename": "jfgl2_20250924_052309.zip", "size": 26888986, "hash": "4a8ec7c76533e4b12d0d98c48baec67c", "url": "http://www.jfglzs.com/software/jfgl2.zip", "url_name": "助手安装文件", "timestamp": "2025-09-24T05:23:38.409677"}, {"success": true, "filepath": "downloads/c1_20250924_052338.html", "filename": "c1_20250924_052338.html", "size": 12376, "hash": "3fc43cb5c5fb76144fb644e5b9e22609", "url": "https://www.jfglzs.com/c1.html", "url_name": "助手发布页", "timestamp": "2025-09-24T05:23:44.175429"}]}
{"timestamp": "2025-09-25T21:14:44.573836", "run_id": "18020866310", "downloads": [{"success": false, "error": "HTTPSConnectionPool(host='www-x-jfglzs-x-com.img.addlink.cn', port=443): Read timed out.", "filename": "jfgl2_20250925_211322.zip", "url": "http://www.jfglzs.com/software/jfgl2.zip", "url_name": "助手安装文件"}]}
{"timestamp": "2025-09-26T01:05:59.982927", "run_id": "18024824098", "downloads": [{"success": true, "filepath": "downloads/jfgl2_20250926_010533.zip", "filename": "jfgl2_20250926_010533.zip", "size": 26888994, "hash": "b95c1fe3d6eb2875ea8b0aa39292198e", "url": "http://www.jfglzs.com/software/jfgl2.zip", "url_name": "助手安装文件", "timestamp": "2025-09-26T01:05:58.941617"}, {"success": true, "filepath": "downloads/c1_20250926_010558.html", "filename": "c1_20250926_010558.html", "size": 12378, "hash": "c70720cd7afdff30478ad66db6d91613", "url": "https://www.jfglzs.com/c1.html", "url_name": "助手发布页", "timestamp": "2025-09-26T01:05:59.981476"}]}
{"timestamp": "2025-09-27T05:14:10.951962", "run_id": "18055472989", "downloads": [{"success": true, "filepath": "downloads/jfgl2_20250927_051356.zip", "filename": "jfgl2_20250927_051356.zip", "size": 26888994, "hash": "b95c1fe3d6eb2875ea8b0aa39292198e", "url": "http://www.jfglzs.com/software/jfgl2.zip", "url_name": "助手安装文件", "timestamp": "2025-09-27T05:14:04.887585"}, {"success": true, "filepath": "downloads/c1_20250927_051404.html", "filename": "c1_20250927_051404.html", "size": 12378, "hash": "c70720cd7afdff30478ad66db6d91613", "url": "https://www.jfglzs.com/c1.html", "url_name": "助手发布页", "timestamp": "2025-09-27T05:14:10.950534"}]}
{"timestamp": "2025-09-28T11:12:15.871763", "run_id": "18073439125", "downloads": [{"success": true, "filepath": "downloads/jfgl2_20250928_111124.zip", "filename": "jfgl2_20250928_111124.zip", "size": 26918835, "hash": "eadff2cd5abf32fd2d7f7a466c92a532", "url": "http://www.jfglzs.com/software/jfgl2.zip", "url_name": "助手安装文件", "timestamp": "2025-09-28T11:12:15.869910"}]}
{"timestamp": "2025-09-29T03:01:44.613436", "run_id": "18084363412", "downloads": [{"success": true, "filepath": "downloads/jfgl2_20250929_030054.zip", "filename": "jfgl2_20250929_030054.zip", "size": 26939925, "hash": "e052a19052fef814159405b1b1ff24c8", "url": "http://www.jfglzs.com/software/jfgl2.zip", "url_name": "助手安装文件", "timestamp": "2025-09-29T03:01:44.611547"}]}
{"timestamp": "2025-09-30T01:06:49.147306", "run_id": "18115310915", "downloads": [{"success": true, "filepath": "downloads/c1_20250930_010648.html", "filename": "c1_20250930_010648.html", "size": 12382, "hash": "24cecac68d32189af42799a8c3f45bd3", "url": "https://www.jfglzs.com/c1.html", "url_name": "助手发布页", "timestamp": "2025-09-30T01:06:49.145987"}]}
{"timestamp": "2025-09-30T11:13:12.766946", "run_id": "18127946452", "downloads": [{"success": true, "filepath": "downloads/jfgl2_20250930_111304.zip", "filename": "jfgl2_20250930_111304.zip", "size": 26937910, "hash": "8b2be9183c3b370c3065253d190d1841", "url": "http://www.jfglzs.com/software/jfgl2.zip", "url_name": "助手安装文件", "timestamp": "2025-09-30T11:13:12.764911"}]}
{"timestamp": "2025-10-01T01:13:35.270201", "run_id": "18148039586", "downloads": [{"success": true, "filepath": "downloads/urls_20251001_011333.txt", "filename": "urls_20251001_011333.txt", "size": 300, "hash": "ba93154bfad7556698e51e2011216cd4", "url": "http://www.zmyxl2016.com/urls.txt", "url_name": "屏蔽网址列表", "timestamp": "2025-10-01T01:13:34.425869"}, {"success": true, "filepath": "downloads/cpm_20251001_011334.txt", "filename": "cpm_20251001_011334.txt", "size": 40, "hash": "5e2abc31cd480ec4258129854ebf0edf", "url": "http://www.zmyxl2008.com/cpm.txt", "url_name": "屏蔽程序特征表", "timestamp": "2025-10-01T01:13:35.269785"}]}
{"timestamp": "2025-10-01T03:07:36.721116", "run_id": "18149999513", "downloads": [{"success": true, "filepath": "downloads/urls_20251001_030735.txt", "filename": "urls_20251001_030735.txt", "size": 285, "hash": "147717f80517222c86b11d1ba778d473", "url": "http://www.zmyxl2016.com/urls.txt", "url_name": "屏蔽网址列表", "timestamp": "2025-10-01T03:07:36.720679"}]}
{"timestamp": "2025-10-02T07:14:07.041914", "run_id": "18186082846", "downloads": [{"success": true, "filepath": "downloads/jfgl2_20251002_071400.zip", "filename": "jfgl2_20251002_071400.zip", "size": 26937910, "hash": "8b2be9183c3b370c3065253d190d1841", "url": "http://www.jfglzs.com/software/jfgl2.zip", "url_name": "助手安装文件", "timestamp": "2025-10-02T07:14:06.212559"}, {"success": true, "filepath": "downloads/c1_20251002_071406.html", "filename": "c1_20251002_071406.html", "size": 12382, "hash": "dd13ad705d87b53e1d31e2defed8509a", "url": "https://www.jfglzs.com/c1.html", "url_name": "助手发布页", "timestamp": "2025-10-02T07:14:07.040432"}]}
{"timestamp": "2025-10-02T15:19:32.846650", "run_id": "18197463897", "downloads": [{"success": true, "filepath": "downloads/kstz_20251002_151932.bin", "filename": "kstz_20251002_151932.bin", "size": 1337, "hash": "d7b37d5aa940862bbfefe81125961c01", "url": "http://ragd.org.cn/kstz", "url_name": "11月业余无线电考试页面", "timestamp": "2025-10-02T15:19:32.846147"}]}
{"timestamp": "2025-10-05T08:18:47.801406", "run_id": "18256165413", "downloads": [{"success": true, "filepath": "downloads/jfgl2_20251005_081756.zip", "filename": "jfgl2_20251005_081756.zip", "size": 26933322, "hash": "b5249132b692eafc84963a2447825f22", "url": "http://www.jfglzs.com/software/jfgl2.zip", "url_name": "助手安装文件", "timestamp": "2025-10-05T08:18:47.023580"}, {"success": true, "filepath": "downloads/c1_20251005_081847.html", "filename": "c1_20251005_081847.html", "size": 12381, "hash": "8b5ec0401817f7b2d6211685ee6c040b", "url": "https://www.jfglzs.com/c1.html", "url_name": "助手发布页", "timestamp": "2025-10-05T08:18:47.800390"}]}
{"timestamp": "2025-10-07T07:15:54.024048", "run_id": "18305034151", "downloads": [{"success": true, "filepath": "downloads/urls_20251007_071553.txt", "filename": "urls_20251007_071553.txt", "size": 308, "hash": "cf0a1e88ff9570a5498c2223ba7e6191", "url": "http://www.zmyxl2016.com/urls.txt", "url_name": "屏蔽网址列表", "timestamp": "2025-10-07T07:15:54.023623"}]}
{"timestamp": "2025-10-07T09:17:11.325676", "run_id": "18307948664", "downloads": [{"success": true, "filepath": "downloads/c1_20251007_091710.html", "filename": "c1_20251007_091710.html", "size": 12491, "hash": "b3f642f19fc4b33d2b332db1c5da89be", "url": "https://www.jfglzs.com/c1.html", "url_name": "助手发布页", "timestamp": "2025-10-07T09:17:11.324238"}]}
{"timestamp": "2025-10-08T02:55:10.827650", "run_id": "18332305047", "downloads": [{"success": true, "filepath": "downloads/cpm_20251008_025505.txt", "filename": "cpm_20251008_025505.txt", "size": 49, "hash": "ae0a5cced5c7ec1d22ceb3a4f0403d6f", "url": "http://www.zmyxl2008.com/cpm.txt", "url_name": "屏蔽程序特征表", "timestamp": "2025-10-08T02:55:10.827242"}]}
{"timestamp": "2025-10-09T01:10:44.594330", "run_id": "18362409023", "downloads": [{"success": true, "filepath": "downloads/jfgl2_20251009_011038.zip", "filename": "jfgl2_20251009_011038.zip", "size": 26938497, "hash": "b34e8c6c9c534f4e6b9310b609def60d", "url": "http://www.jfglzs.com/software/jfgl2.zip", "url_name": "助手安装文件", "timestamp": "2025-10-09T01:10:44.592889"}]}
{"timestamp": "2025-10-11T01:08:18.462479", "run_id": "18422110068", "downloads": [{"success": true, "filepath": "downloads/cpm_20251011_010817.txt", "filename": "cpm_20251011_010817.txt", "size": 103, "hash": "b8ac76daef05142f727f337fca105055", "url": "http://www.zmyxl2008.com/cpm.txt", "url_name": "屏蔽程序特征表", "timestamp": "2025-10-11T01:08:18.462099"}]}
{"timestamp": "2025-10-11T02:51:50.542952", "run_id": "18423322268", "downloads": [{"success": true, "filepath": "downloads/cpm_20251011_025149.txt", "filename": "cpm_20251011_025149.txt", "size": 81, "hash": "b3f530c0d53e548dbe28fb39d349712b", "url": "http://www.zmyxl2008.com/cpm.txt", "url_name": "屏蔽程序特征表", "timestamp": "2025-10-11T02:51:50.542354"}]}
{"timestamp": "2025-10-11T06:21:38.132415", "run_id": "18425602015", "downloads": [{"success": true, "filepath": "downloads/cpm_20251011_062137.txt", "filename": "cpm_20251011_062137.txt", "size": 88, "hash": "f0d645128f0d489abe0d57e7014b7fe6", "url": "http://www.zmyxl2008.com/cpm.txt", "url_name": "屏蔽程序特征表", "timestamp": "2025-10-11T06:21:38.132014"}]}
{"timestamp": "2025-10-12T09:15:03.126143", "run_id": "18441957385", "downloads": [{"success": true, "filepath": "downloads/jfgl2_20251012_091450.zip", "filename": "jfgl2_20251012_091450.zip", "size": 26940435, "hash": "470816059fc7999b779e0464705e2971", "url": "http://www.jfglzs.com/software/jfgl2.zip", "url_name": "助手安装文件", "timestamp": "2025-10-12T09:15:03.124331"}]}
